{"cameraMode":{"drawMode":0,"name":"Shaded","section":"Shading Mode"},"sceneLighting":false,"audioPlay":false,"sceneViewState":{"m_AlwaysRefresh":false,"showFog":true,"showSkybox":false,"showFlares":true,"showImageEffects":true,"showParticleSystems":true,"showVisualEffectGraphs":true,"m_FxEnabled":true},"in2DMode":false,"pivot":{"x":0.031422168016433719,"y":-0.02731078863143921,"z":-0.05178055167198181},"rotation":{"x":0.03975898027420044,"y":-0.9601607322692871,"z":0.1890401393175125,"w":0.20193862915039063},"size":0.2442360669374466,"orthographic":false}